MANIFEST.in
README.txt
setup.py
docs/HISTORY.txt
docs/LICENSE.txt
src/silva/__init__.py
src/silva.core.services.egg-info/PKG-INFO
src/silva.core.services.egg-info/SOURCES.txt
src/silva.core.services.egg-info/dependency_links.txt
src/silva.core.services.egg-info/namespace_packages.txt
src/silva.core.services.egg-info/not-zip-safe
src/silva.core.services.egg-info/requires.txt
src/silva.core.services.egg-info/top_level.txt
src/silva/core/__init__.py
src/silva/core/services/__init__.py
src/silva/core/services/base.py
src/silva/core/services/catalog.py
src/silva/core/services/configure.zcml
src/silva/core/services/delayed.py
src/silva/core/services/interfaces.py
src/silva/core/services/secret.png
src/silva/core/services/secret.py
src/silva/core/services/splitter.py
src/silva/core/services/utils.py
src/silva/core/services/tests/__init__.py
src/silva/core/services/tests/test_secret.py
src/silva/core/services/tests/test_utils.py