Metadata-Version: 1.1
Name: silva.core.services
Version: 3.0.1
Summary: Configuration services for Silva CMS
Home-page: https://github.com/silvacms/silva.core.services
Author: Infrae
Author-email: info@infrae.com
License: BSD
Keywords: silva core services
Platform: UNKNOWN
Classifier: Framework :: Zope2
Classifier: License :: OSI Approved :: BSD License
Classifier: Programming Language :: Python
Classifier: Topic :: Software Development :: Libraries :: Python Modules
